{
  "project_info": {
    "project_number": "98490570517",
    "project_id": "coffe-shop-6cd83",
    "storage_bucket": "coffe-shop-6cd83.firebasestorage.app"
  },
  "client": [
    {
      "client_info": {
        "mobilesdk_app_id": "1:98490570517:android:82770052dfe3df96debb1c",
        "android_client_info": {
          "package_name": "com.example.smartcanteen_app"
        }
      },
      "oauth_client": [],
      "api_key": [
        {
          "current_key": "AIzaSyCukaVYw9Lmj65lZTDZgCwDpktL9K-2l0k"
        }
      ],
      "services": {
        "appinvite_service": {
          "other_platform_oauth_client": []
        }
      }
    }
  ],
  "configuration_version": "1"
}